_nvx_utf8validator.abi3.so
_nvx_xormasker.abi3.so
autobahn/__init__.py
autobahn/__main__.py
autobahn/_version.py
autobahn/exception.py
autobahn/testutil.py
autobahn/util.py
autobahn/asset/xbr_gray.svg
autobahn/asset/xbr_white.svg
autobahn/asyncio/__init__.py
autobahn/asyncio/component.py
autobahn/asyncio/rawsocket.py
autobahn/asyncio/util.py
autobahn/asyncio/wamp.py
autobahn/asyncio/websocket.py
autobahn/asyncio/test/README_NO_INIT_PY
autobahn/asyncio/test/test_aio_rawsocket.py
autobahn/asyncio/test/test_aio_websocket.py
autobahn/asyncio/test/test_wamp_runner.py
autobahn/nvx/__init__.py
autobahn/nvx/_compile_args.py
autobahn/nvx/_utf8validator.c
autobahn/nvx/_utf8validator.py
autobahn/nvx/_xormasker.c
autobahn/nvx/_xormasker.py
autobahn/nvx/test/__init__.py
autobahn/nvx/test/test_nvx_utf8validator.py
autobahn/rawsocket/__init__.py
autobahn/rawsocket/util.py
autobahn/rawsocket/test/__init__.py
autobahn/rawsocket/test/test_rawsocket_url.py
autobahn/test/__init__.py
autobahn/test/test_rng.py
autobahn/test/test_util.py
autobahn/twisted/__init__.py
autobahn/twisted/choosereactor.py
autobahn/twisted/component.py
autobahn/twisted/cryptosign.py
autobahn/twisted/forwarder.py
autobahn/twisted/rawsocket.py
autobahn/twisted/resource.py
autobahn/twisted/util.py
autobahn/twisted/wamp.py
autobahn/twisted/websocket.py
autobahn/twisted/test/__init__.py
autobahn/twisted/test/test_tx_application_runner.py
autobahn/twisted/test/test_tx_choosereactor.py
autobahn/twisted/test/test_tx_component.py
autobahn/twisted/test/test_tx_endpoint_plugins.py
autobahn/twisted/test/test_tx_protocol.py
autobahn/twisted/test/test_tx_rawsocket.py
autobahn/twisted/test/test_tx_websocket_agent.py
autobahn/twisted/test/test_wamp_runner.py
autobahn/twisted/testing/__init__.py
autobahn/wamp/__init__.py
autobahn/wamp/auth.py
autobahn/wamp/component.py
autobahn/wamp/cryptobox.py
autobahn/wamp/cryptosign.py
autobahn/wamp/exception.py
autobahn-25.10.2.dist-info/METADATA
autobahn-25.10.2.dist-info/WHEEL
autobahn-25.10.2.dist-info/entry_points.txt
autobahn-25.10.2.dist-info/top_level.txt
autobahn-25.10.2.dist-info/RECORD
autobahn-25.10.2.dist-info/licenses/LICENSE
