Metadata-Version: 2.4
Name: autobahn
Version: 25.10.2
Summary: WebSocket client & server library, WAMP real-time framework
Author-email: typedef int GmbH <contact@typedefint.eu>
License-Expression: MIT
Project-URL: Homepage, https://autobahn.readthedocs.io/
Project-URL: Source, https://github.com/crossbario/autobahn-python
Keywords: autobahn,crossbar,websocket,realtime,rfc6455,wamp,rpc,pubsub,twisted,asyncio
Classifier: Development Status :: 5 - Production/Stable
Classifier: Environment :: No Input/Output (Daemon)
Classifier: Framework :: Twisted
Classifier: Intended Audience :: Developers
Classifier: Operating System :: OS Independent
Classifier: Programming Language :: Python
Classifier: Programming Language :: Python :: 3
Classifier: Programming Language :: Python :: 3.11
Classifier: Programming Language :: Python :: 3.12
Classifier: Programming Language :: Python :: 3.13
Classifier: Programming Language :: Python :: 3.14
Classifier: Programming Language :: Python :: Implementation :: CPython
Classifier: Programming Language :: Python :: Implementation :: PyPy
Classifier: Topic :: Internet
Classifier: Topic :: Internet :: WWW/HTTP
Classifier: Topic :: Communications
Classifier: Topic :: System :: Distributed Computing
Classifier: Topic :: Software Development :: Libraries
Classifier: Topic :: Software Development :: Libraries :: Python Modules
Classifier: Topic :: Software Development :: Object Brokering
Requires-Python: >=3.11
License-File: LICENSE
Requires-Dist: txaio>=25.9.2
Requires-Dist: cryptography>=3.4.6
Requires-Dist: hyperlink>=21.0.0
Requires-Dist: importlib-resources>=5.0.0; python_version < "3.10"
Provides-Extra: twisted
Requires-Dist: zope.interface>=5.2.0; extra == "twisted"
Requires-Dist: twisted>=22.10.0; extra == "twisted"
Requires-Dist: attrs>=20.3.0; extra == "twisted"
Provides-Extra: accelerate
Provides-Extra: compress
Requires-Dist: python-snappy>=0.6.0; extra == "compress"
Provides-Extra: serialization
Requires-Dist: msgpack>=1.0.2; platform_python_implementation == "CPython" and extra == "serialization"
Requires-Dist: ujson>=4.0.2; platform_python_implementation == "CPython" and extra == "serialization"
Requires-Dist: u-msgpack-python>=2.1; platform_python_implementation != "CPython" and extra == "serialization"
Requires-Dist: cbor2>=5.2.0; extra == "serialization"
Requires-Dist: py-ubjson>=0.16.1; extra == "serialization"
Requires-Dist: flatbuffers>=22.12.6; extra == "serialization"
Provides-Extra: encryption
Requires-Dist: pyopenssl>=20.0.1; extra == "encryption"
Requires-Dist: service-identity>=18.1.0; extra == "encryption"
Requires-Dist: pynacl>=1.4.0; extra == "encryption"
Requires-Dist: pytrie>=0.4.0; extra == "encryption"
Requires-Dist: qrcode>=7.3.1; extra == "encryption"
Requires-Dist: base58>=2.1.1; extra == "encryption"
Requires-Dist: ecdsa>=0.19.1; extra == "encryption"
Provides-Extra: scram
Requires-Dist: cffi>=1.14.5; extra == "scram"
Requires-Dist: argon2-cffi>=20.1.0; extra == "scram"
Requires-Dist: passlib>=1.7.4; extra == "scram"
Provides-Extra: nvx
Requires-Dist: cffi>=1.14.5; extra == "nvx"
Provides-Extra: build-tools
Requires-Dist: build>=1.0.0; extra == "build-tools"
Requires-Dist: wheel>=0.36.2; extra == "build-tools"
Requires-Dist: auditwheel>=5.0.0; sys_platform == "linux" and extra == "build-tools"
Provides-Extra: dev
Requires-Dist: auditwheel>=5.0.0; sys_platform == "linux" and extra == "dev"
Requires-Dist: backports.tempfile>=1.0; extra == "dev"
Requires-Dist: build>=1.0.0; extra == "dev"
Requires-Dist: bumpversion>=0.5.3; extra == "dev"
Requires-Dist: codecov>=2.0.15; extra == "dev"
Requires-Dist: humanize>=0.5.1; extra == "dev"
Requires-Dist: mypy>=0.610; (python_version >= "3.4" and platform_python_implementation != "PyPy") and extra == "dev"
Requires-Dist: myst-parser>=4.0.1; extra == "dev"
Requires-Dist: passlib; extra == "dev"
Requires-Dist: pep8-naming>=0.3.3; extra == "dev"
Requires-Dist: pyenchant>=1.6.6; extra == "dev"
Requires-Dist: pyflakes>=1.0.0; extra == "dev"
Requires-Dist: pyinstaller>=4.2; extra == "dev"
Requires-Dist: pylint>=1.9.2; extra == "dev"
Requires-Dist: pytest-aiohttp; extra == "dev"
Requires-Dist: pytest-asyncio>=0.14.0; extra == "dev"
Requires-Dist: pytest-runner>=2.11.1; extra == "dev"
Requires-Dist: pytest>=3.4.2; extra == "dev"
Requires-Dist: pyyaml>=4.2b4; extra == "dev"
Requires-Dist: qualname>=0.1.0; extra == "dev"
Requires-Dist: ruff>=0.12.1; extra == "dev"
Requires-Dist: sphinx-autoapi>=1.7.0; extra == "dev"
Requires-Dist: sphinx<8,>=1.7.1; extra == "dev"
Requires-Dist: sphinx-rtd-theme>=0.1.9; extra == "dev"
Requires-Dist: sphinxcontrib-images>=0.9.1; extra == "dev"
Requires-Dist: twine>=3.3.0; extra == "dev"
Requires-Dist: twisted>=22.10.0; extra == "dev"
Requires-Dist: txaio>=25.9.2; extra == "dev"
Requires-Dist: watchdog>=0.8.3; extra == "dev"
Requires-Dist: wheel>=0.36.2; extra == "dev"
Requires-Dist: yapf==0.29.0; extra == "dev"
Provides-Extra: all
Requires-Dist: autobahn[accelerate,compress,encryption,nvx,scram,serialization,twisted]; extra == "all"
Provides-Extra: asyncio
Dynamic: license-file
